somerandomapi/__init__.py
somerandomapi/enums.py
somerandomapi/errors.py
somerandomapi/utils.py
somerandomapi/clients/__init__.py
somerandomapi/clients/abc.py
somerandomapi/clients/animal.py
somerandomapi/clients/animu.py
somerandomapi/clients/canvas.py
somerandomapi/clients/chatbot.py
somerandomapi/clients/client.py
somerandomapi/clients/pokemon.py
somerandomapi/clients/premium.py
somerandomapi/internals/endpoints.py
somerandomapi/internals/http.py
somerandomapi/models/__init__.py
somerandomapi/models/abc.py
somerandomapi/models/animal_fact.py
somerandomapi/models/animu.py
somerandomapi/models/chatbot.py
somerandomapi/models/encoding.py
somerandomapi/models/image.py
somerandomapi/models/lyrics.py
somerandomapi/models/namecard.py
somerandomapi/models/pokemon.py
somerandomapi/models/rankcard.py
somerandomapi/models/rgb.py
somerandomapi/models/tweet.py
somerandomapi/models/youtube_comment.py
somerandomapi/models/welcome/__init__.py
somerandomapi/models/welcome/free.py
somerandomapi/models/welcome/premium.py
somerandomapi/types/__init__.py
somerandomapi/types/animal.py
somerandomapi/types/animu.py
somerandomapi/types/canvas.py
somerandomapi/types/facts.py
somerandomapi/types/http.py
somerandomapi/types/img.py
somerandomapi/types/pokemon.py
somerandomapi/types/premium.py
somerandomapi_py-0.1.3.dist-info/licenses/LICENSE
somerandomapi_py-0.1.3.dist-info/METADATA
somerandomapi_py-0.1.3.dist-info/WHEEL
somerandomapi_py-0.1.3.dist-info/top_level.txt
somerandomapi_py-0.1.3.dist-info/RECORD
