Metadata-Version: 2.4
Name: somerandomapi.py
Version: 0.1.3
Summary: An actively maintained wrapper for the somerandomapi API.
Author: Soheab_
License-Expression: MPL-2.0
Project-URL: homepage, https://github.com/Soheab/somerandomapi.py
Project-URL: documentation, https://somerandomapipy.readthedocs.io/
Project-URL: repository, https://github.com/Soheab/somerandomapi.py
Keywords: https://some-random-api.com,https://api.some-random-api.com,some-random-api,api,somerandomapi,random,images,fun,discord,discord.py,generation,rankcard,canvas,welcome,free,open-source,asyncio,aiohttp,async,wrapper
Classifier: Development Status :: 5 - Production/Stable
Classifier: Natural Language :: English
Classifier: Typing :: Typed
Classifier: Programming Language :: Python :: 3 :: Only
Classifier: Programming Language :: Python :: 3.11
Classifier: Programming Language :: Python :: 3.12
Classifier: Programming Language :: Python :: 3.13
Classifier: Programming Language :: Python :: 3.14
Requires-Python: >=3.11
License-File: LICENSE
Requires-Dist: aiohttp<4.0.0,>=3.10.0
Provides-Extra: docs
Requires-Dist: Sphinx<9,>=8.2; extra == "docs"
Requires-Dist: furo<2025,>=2024.8; extra == "docs"
Requires-Dist: sphinx-autodoc-typehints<4,>=3.2; extra == "docs"
Requires-Dist: enum-tools[sphinx]<0.14,>=0.13; extra == "docs"
Provides-Extra: dev
Requires-Dist: ruff==0.11.8; extra == "dev"
Dynamic: license-file
